{
	"15033616": {

		"NAME": "MiseqRUO",
		
		"ASSY,CABLES,INSTRUMENT" : 1,

		"ASSY,IMAGING MODULE, DIE CAST, MiSeq" : 1,

		"ASSY,CHASSIS,MISEQ" : 1,

		"MiSeq, EBOX, NO DRIVES, WIN10 SBC" : 1,

		"ASSY,SIPPER CONSOLE" : 1,

		"DUCT,CHILLER" : 1,

		"COVER,Y-STAGE" : 1,

		"CABLE ASSY,ValvePigtail-EXT" : 1,

		"ASSY,TB,RGT VALVE TO FC INLET,S-16372-2" : 1,

		"ASSY, LED MODULE, PT39-L51 & 10R200" : 1,

		"CABLE ASSY,24PortValvePwrComm" : 1,

		"ASSY, Z STAGE, OBJECTIVE, MISEQ" : 1,

		"ASSY,RUO,CAM MOD,DIE CAST PNLS,CAMERA 1" : 1,

		"MISEQ, ASSY, COMPENSATOR WITH MOTOR, V2" : 1,

		"ASSY,RUO,CAM MOD,DIE CAST PNLS,CAMERA 2" : 1,

		"ASSY, CHILLER, MiSeq" : 1,

		"ASSY, SYRINGE PUMP SOLENOID + BRACKET" : 1,

		"CABLE ASSY,FLOW SENSORS(RHEODYNE)" : 1,

		"PLUG,6-40,FLAT BOTTOM,PEEK" : 1,

		"ASSY,VALVE,ROTARY,24POS,SMT,/BRACKET": 1,

		"ASSY, FCH TEC" : 1,

		"COVER,THIN,CLAMP,SINGLE,FCH" : 1,

		"COVER,REAR,INTRLCKNG,LARGE CLEARANCE,FCH" : 1,

		"COVER,RFID MOLDED,FCH" : 1,

		"ASSY,FCH RFID,SPLIT,COATED,W CABLE" : 1,

		"SKID PLATE,Y-STAGE CABLES" : 1,

		"ASSY,EXHAUST FAN" : 1,

		"CABLE ASSY,INSTRUMENT/FLOWCELLFAN" : 1,

		"CABLE ASSY,LED FAN" : 1,

		"BRKT,CONNECTOR MOUNT" : 1,

		"MISEQ, EBOX, NO DRIVES, WIN10 SBC" : 1,

		"MISEQ, SOLID STATE DRIVE, 1TB" : 1
	},
	

	"20014737": {

		"NAME": "MiseqDx",
		
		"20003526" :["ASSY,CABLES,INSTRUMENT", 1],

		"15033631" :["ASSY,IMAGING MODULE, DIE CAST, MiSeq", 1],

		"20018591" :["ASSY,CHASSIS,MISEQ", 1],

		"15023658" :["DUCT,CHILLER", 1],

		"15031701" :["COVER,Y-STAGE", 1],

		"15026993" :["CABLE ASSY,ValvePigtail-EXT", 1],

		"15023095" :["ASSY,TB,RGT VALVE TO FC INLET,S-16372-2", 1],

		"20045848" :["ASSY, LED MODULE, PT39-L51 & 10R200", 1],

		"15027051" :["CABLE ASSY,24PortValvePwrComm", 1],

		"20000525" :["ASSY, Z STAGE, OBJECTIVE, MISEQ", 1],

		"20031173" :["ASSY,DX,CAMERA MODULE2,SONY,CAMERA 1", 1],

		"20042278" :["MISEQ, ASSY, COMPENSATOR WITH MOTOR, V2", 1],

		"15072605" :["ASSY, CHILLER, MiSeq", 1],

		"20025890" :["ASSY, SYRINGE PUMP SOLENOID + BRACKET", 1],

		"15022949" :["CABLE ASSY,FLOW SENSORS(RHEODYNE)", 1],

		"15038429" :["PLUG,6-40,FLAT BOTTOM,PEEK", 1],

		"20004531" :["ASSY,VALVE,ROTARY,24POS,SMT,W/BRACKET", 1],

		"15051681" :["ASSY, FCH TEC", 1],

		"15024044" :["COVER,THIN,CLAMP,SINGLE,FCH", 1],
		
		"15027803" :["COVER,REAR,INTRLCKNG,LARGE CLEARANCE,FCH", 1],

		"15027838" :["COVER,RFID MOLDED,FCH", 1],

		"15029460" :["ASSY,FCH RFID,SPLIT,COATED,W CABLE", 1],

		"15026880" :["SKID PLATE,Y-STAGE CABLES", 1],

		"15023704" :["ASSY,EXHAUST FAN", 1],

		"15029939" :["CABLE ASSY,INSTRUMENT/FLOWCELLFAN", 1],

		"15026686" :["CABLE ASSY,LED FAN", 1],

		"15026509" :["BRKT,CONNECTOR MOUNT", 1],

		"20019541" :["MiSeq,E-BOX,NO DRIVES",1],

		"15038048" :["ASSY,SIPPER CONSOLE, MiSeqDx", 1],

		"20015973" :["MISEQ, SOLID STATE DRIVE, 1TB", 1],

		"15037979" :["ASSY,REAGENT DOOR, MiSeqDx", 1],

		"15036214" :["ASSY,LEFT FRONT COVER,MiSeqDx", 1],

		"20003486" :["ASSY,LEFT COVER", 1],

		"20032895" :["Assy,Enclosure,Rt Pnl,Cu Coated,MiSeqDx", 1],

		"20001313" :["ENCLOSURE, BACK PANEL, DX", 1],

		"15037974" :["ENCLOSURE,TOP PANEL, Dx", 1],
		
		"15041807" :["MS#-PR2, INCORPORATION BUFFER,FIN REAG", 1],

		"15028382" :["FLOWCELL,MiSeq,V2.0, PE-GRAFTED", 1],

		"15043895" :["MiSeq® RGT Kit v3 600 cyc PE-Bx 1 of 2", 1]
	},

	"15048976": {

		"NAME": "MiseqFGx",
	
		"20003526" :["ASSY,CABLES,INSTRUMENT", 1],

		"15033631" :["ASSY,IMAGING MODULE, DIE CAST, MiSeq", 1],

		"20018591" :["ASSY,CHASSIS,MISEQ", 1],

		"15023658" :["DUCT,CHILLER", 1],

		"15031701" :["COVER,Y-STAGE", 1],

		"15026993" :["CABLE ASSY,ValvePigtail-EXT", 1],

		"15023095" :["ASSY,TB,RGT VALVE TO FC INLET,S-16372-2", 1],

		"20045848" :["ASSY, LED MODULE, PT39-L51 & 10R200", 1],

		"15027051" :["CABLE ASSY,24PortValvePwrComm", 1],

		"20000525" :["ASSY, Z STAGE, OBJECTIVE, MISEQ", 1],

		"20031173" :["ASSY,DX,CAMERA MODULE2,SONY,CAMERA 1", 1],

		"20042278" :["MISEQ, ASSY, COMPENSATOR WITH MOTOR, V2", 1],

		"15072605" :["ASSY, CHILLER, MiSeq", 1],

		"20025890" :["ASSY, SYRINGE PUMP SOLENOID + BRACKET", 1],

		"15022949" :["CABLE ASSY,FLOW SENSORS(RHEODYNE)", 1],

		"15038429" :["PLUG,6-40,FLAT BOTTOM,PEEK", 1],

		"20004531" :["ASSY,VALVE,ROTARY,24POS,SMT,W/BRACKET", 1],

		"15051681" :["ASSY, FCH TEC", 1],

		"15024044" :["COVER,THIN,CLAMP,SINGLE,FCH", 1],
		
		"15027803" :["COVER,REAR,INTRLCKNG,LARGE CLEARANCE,FCH", 1],

		"15027838" :["COVER,RFID MOLDED,FCH", 1],

		"15029460" :["ASSY,FCH RFID,SPLIT,COATED,W CABLE", 1],

		"15026880" :["SKID PLATE,Y-STAGE CABLES", 1],

		"15023704" :["ASSY,EXHAUST FAN", 1],

		"15029939" :["CABLE ASSY,INSTRUMENT/FLOWCELLFAN", 1],

		"15026686" :["CABLE ASSY,LED FAN", 1],

		"15026509" :["BRKT,CONNECTOR MOUNT", 1],

		"20019541" :["MiSeq,E-BOX,NO DRIVES",1],

		"15038048" :["ASSY,SIPPER CONSOLE, MiSeqDx", 1],

		"20015973" :["MISEQ, SOLID STATE DRIVE, 1TB", 1]
	},

	"20014054": {

		"NAME": "MiseqDxChina",
		
		"20003526" :["ASSY,CABLES,INSTRUMENT", 1],

		"15033631" :["ASSY,IMAGING MODULE, DIE CAST, MiSeq", 1],

		"20018591" :["ASSY,CHASSIS,MISEQ", 1],

		"15023658" :["DUCT,CHILLER", 1],

		"15031701" :["COVER,Y-STAGE", 1],

		"15026993" :["CABLE ASSY,ValvePigtail-EXT", 1],

		"15023095" :["ASSY,TB,RGT VALVE TO FC INLET,S-16372-2", 1],

		"20045848" :["ASSY, LED MODULE, PT39-L51 & 10R200", 1],

		"15027051" :["CABLE ASSY,24PortValvePwrComm", 1],

		"20000525" :["ASSY, Z STAGE, OBJECTIVE, MISEQ", 1],

		"20031173" :["ASSY,DX,CAMERA MODULE2,SONY,CAMERA 1", 1],

		"20042278" :["MISEQ, ASSY, COMPENSATOR WITH MOTOR, V2", 1],

		"15072605" :["ASSY, CHILLER, MiSeq", 1],

		"20025890" :["ASSY, SYRINGE PUMP SOLENOID + BRACKET", 1],

		"15022949" :["CABLE ASSY,FLOW SENSORS(RHEODYNE)", 1],

		"15038429" :["PLUG,6-40,FLAT BOTTOM,PEEK", 1],

		"20004531" :["ASSY,VALVE,ROTARY,24POS,SMT,W/BRACKET", 1],

		"15051681" :["ASSY, FCH TEC", 1],

		"15024044" :["COVER,THIN,CLAMP,SINGLE,FCH", 1],
		
		"15027803" :["COVER,REAR,INTRLCKNG,LARGE CLEARANCE,FCH", 1],

		"15027838" :["COVER,RFID MOLDED,FCH", 1],

		"15029460" :["ASSY,FCH RFID,SPLIT,COATED,W CABLE", 1],

		"15026880" :["SKID PLATE,Y-STAGE CABLES", 1],

		"15023704" :["ASSY,EXHAUST FAN", 1],

		"15029939" :["CABLE ASSY,INSTRUMENT/FLOWCELLFAN", 1],

		"15026686" :["CABLE ASSY,LED FAN", 1],

		"15026509" :["BRKT,CONNECTOR MOUNT", 1],

		"20019541" :["MiSeq,E-BOX,NO DRIVES",1],

		"15038048" :["ASSY,SIPPER CONSOLE, MiSeqDx", 1],

		"20015973" :["MISEQ, SOLID STATE DRIVE, 1TB", 2],

		"15037979" :["ASSY,REAGENT DOOR, MiSeqDx", 1],

		"15036214" :["ASSY,LEFT FRONT COVER,MiSeqDx", 1],

		"20003486" :["ASSY,LEFT COVER", 1],

		"20032895" :["Assy,Enclosure,Rt Pnl,Cu Coated,MiSeqDx", 1],

		"20001313" :["ENCLOSURE, BACK PANEL, DX", 1],

		"15037974" :["ENCLOSURE,TOP PANEL, Dx", 1],
		
		"15041807" :["MS#-PR2, INCORPORATION BUFFER,FIN REAG", 1],

		"15028382" :["FLOWCELL,MiSeq,V2.0, PE-GRAFTED", 1],

		"15043895" :["MiSeq® RGT Kit v3 600 cyc PE-Bx 1 of 2", 1]
	},

	"20044796": {

		"NAME": "NovaseqDx",

		"20013650" :["SHIPPING BRKT, FLUIDICS MODULE, CUSTOM", 2], 

		"20013559" :["DUCT, TUBING", 1], 

		"20016485" :["ASSY, RCA, TL, NOVASEQ", 2], 

		"20016511" :["ASSY, PHANTOM BIM, TL", 2], 

		"20011230" :["BRACKET, TUBE SUPPORT", 1], 

		"20016545" :["CBL,APX_MISC_H22-OM GROUNDING_FORK", 2],

		"20036748" :["ASSY, FLUIDICS, MODULE,V2", 1],

		"15043544" :["PCA, RFID Integrated Antenna", 1], 

		"20019247" :["ASSEMBLY, CABLE TRACK", 1], 

		"20011708" :["VIB ISOLATOR ASSY, TUNED DAMPER, REAR", 2], 

		"20011707" :["VIB ISOLATOR ASSY, TUNED DAMPER, FRONT", 2], 

		"20013725" :["MOTION CONTROLLER, C413", 1], 

		"20043396" :["ASSY, NOVASEQ, COMPUTE ENGINE (CE), CH", 1],

		"20019262" :["ASSY, OPA W/ NOZZLE", 1], 

		"20013665" :["ASSY, XY STAGE MODULE", 1], 

		"20007747" :["ASSY, CAMERA MODULE (CAM)", 1],

		"20007746" :["ASSY, FOCUS TRACKING MODULE (FTM)", 1],

		"20007742" :["ASSY, EMISSION OPTICS MODULE (EOM)", 1],

		"20025662" :["LGM_VES", 1],

		"20046973" :["ASSY, CHASSIS, NOVASEQ, V2", 1],

		"20023899" :["ASSY, DUAL ACTUATION DECK 2.0", 1], 

		"20045692" :["ASSY, COMPUTE ENGINE, V202_A", 1]
	},

	"20013740": {

		"NAME": "NovaseqRUO",
		
		"20013650":["SHIPPING BRKT, FLUIDICS MODULE, CUSTOM", 2], 

		"20013559" :["DUCT, TUBING", 1], 

		"20016485" :["ASSY, RCA, TL, NOVASEQ", 2], 

		"20016511" :["ASSY, PHANTOM BIM, TL", 2], 

		"20011230" :["BRACKET, TUBE SUPPORT", 1], 

		"20016545" :["CBL,APX_MISC_H22-OM GROUNDING_FORK", 2],

		"20036748" :["ASSY, FLUIDICS, MODULE,V2", 1],

		"15043544" :["PCA, RFID Integrated Antenna", 1], 

		"20019247" :["ASSEMBLY, CABLE TRACK", 1], 

		"20011708" :["VIB ISOLATOR ASSY, TUNED DAMPER, REAR", 2], 

		"20011707" :["VIB ISOLATOR ASSY, TUNED DAMPER, FRONT", 2], 

		"20013725" :["MOTION CONTROLLER, C413", 1], 

		"20039412" :["ASSY,COMPUTE ENGINE, NORTHSHORE,NOVASEQ", 1],

		"20019262" :["ASSY, OPA W/ NOZZLE", 1], 

		"20013665" :["ASSY, XY STAGE MODULE", 1], 

		"20007747" :["ASSY, CAMERA MODULE (CAM)", 1],

		"20007746" :["ASSY, FOCUS TRACKING MODULE (FTM)", 1],

		"20007742" :["ASSY, EMISSION OPTICS MODULE (EOM)", 1],

		"20025662" :["LGM_VES", 1],

		"20049345" :["ASSY, CHASSIS, NOVASEQ, V1.5", 1],

		"20023899" :["ASSY, DUAL ACTUATION DECK 2.0", 1]
	},

	"20046751": {

		"NAME": "NovaseqChina",
		
		"20013650":["SHIPPING BRKT, FLUIDICS MODULE, CUSTOM", 2], 

		"20013559" :["DUCT, TUBING", 1], 

		"20016485" :["ASSY, RCA, TL, NOVASEQ", 2], 

		"20016511" :["ASSY, PHANTOM BIM, TL", 2], 

		"20011230" :["BRACKET, TUBE SUPPORT", 1], 

		"20016545" :["CBL,APX_MISC_H22-OM GROUNDING_FORK", 2],

		"20036748" :["ASSY, FLUIDICS, MODULE,V2", 1],

		"15043544" :["PCA, RFID Integrated Antenna", 1], 

		"20019247" :["ASSEMBLY, CABLE TRACK", 1], 

		"20011708" :["VIB ISOLATOR ASSY, TUNED DAMPER, REAR", 2], 

		"20011707" :["VIB ISOLATOR ASSY, TUNED DAMPER, FRONT", 2], 

		"20013725" :["MOTION CONTROLLER, C413", 1], 

		"20043396" :["ASSY, NOVASEQ, COMPUTE ENGINE (CE), CH", 1],

		"20019262" :["ASSY, OPA W/ NOZZLE", 1], 

		"20013665" :["ASSY, XY STAGE MODULE", 1], 

		"20007747" :["ASSY, CAMERA MODULE (CAM)", 1],

		"20007746" :["ASSY, FOCUS TRACKING MODULE (FTM)", 1],

		"20007742" :["ASSY, EMISSION OPTICS MODULE (EOM)", 1],

		"20025662" :["LGM_VES", 1],

		"20046973" :["ASSY, CHASSIS, NOVASEQ, V2", 1],

		"20023899" :["ASSY, DUAL ACTUATION DECK 2.0", 1]
	}
}